tts_webui_extension/vall_e_x/__init__.py
tts_webui_extension/vall_e_x/api.py
tts_webui_extension/vall_e_x/demo.py
tts_webui_extension/vall_e_x/main.py
tts_webui_extension/vall_e_x/test_api.py
tts_webui_extension/vall_e_x/test_gradio_api.py
tts_webui_extension_vall_e_x-0.1.2.dist-info/licenses/LICENSE
tts_webui_extension_vall_e_x-0.1.2.dist-info/METADATA
tts_webui_extension_vall_e_x-0.1.2.dist-info/WHEEL
tts_webui_extension_vall_e_x-0.1.2.dist-info/top_level.txt
tts_webui_extension_vall_e_x-0.1.2.dist-info/RECORD
