Metadata-Version: 2.4
Name: tts_webui_extension.vall_e_x
Version: 0.1.2
Summary: Vall-E-X: Multilingual text-to-speech model supporting English, Chinese, and Japanese
Author: rsxdalv
Project-URL: Homepage, https://github.com/rsxdalv/tts_webui_extension.vall_e_x
Classifier: Programming Language :: Python :: 3
Classifier: License :: OSI Approved :: MIT License
Classifier: Operating System :: OS Independent
Requires-Python: >=3.7
License-File: LICENSE
Requires-Dist: tts-webui.valle-x>=0.0.3
Dynamic: license-file
